pgengine/__init__.py
pgengine/engine.py
pgengine/matrix.py
Pigeons_Game_Engine-0.1.0.dist-info/METADATA
Pigeons_Game_Engine-0.1.0.dist-info/WHEEL
Pigeons_Game_Engine-0.1.0.dist-info/top_level.txt
Pigeons_Game_Engine-0.1.0.dist-info/RECORD
