Metadata-Version: 2.1
Name: Pigeons-Game-Engine
Version: 0.1.0
Summary: Game Engine for Python called Pigeons Game Engine
Author: Damandes
License: MIT
Requires-Dist: keyboard
